{
  "_format": "hh-sol-cache-2",
  "files": {
    "C:\\Users\\user\\projects\\ekolance\\votingApplication\\IVotingContract-Solidity\\contracts\\Election.sol": {
      "lastModificationDate": 1655320862892,
      "contentHash": "7b828abbe1575ae85e065237a1139653",
      "sourceName": "contracts/Election.sol",
      "solcConfig": {
        "version": "0.8.4",
        "settings": {
          "optimizer": {
            "enabled": false,
            "runs": 200
          },
          "outputSelection": {
            "*": {
              "*": [
                "abi",
                "evm.bytecode",
                "evm.deployedBytecode",
                "evm.methodIdentifiers",
                "metadata"
              ],
              "": [
                "ast"
              ]
            }
          }
        }
      },
      "imports": [
        "hardhat/console.sol"
      ],
      "versionPragmas": [
        "^0.8.0"
      ],
      "artifacts": [
        "Election"
      ]
    },
    "C:\\Users\\user\\projects\\ekolance\\votingApplication\\IVotingContract-Solidity\\node_modules\\hardhat\\console.sol": {
      "lastModificationDate": 1655315877968,
      "contentHash": "cc4777addd464ea56fa35b1c45df0591",
      "sourceName": "hardhat/console.sol",
      "solcConfig": {
        "version": "0.8.4",
        "settings": {
          "optimizer": {
            "enabled": false,
            "runs": 200
          },
          "outputSelection": {
            "*": {
              "*": [
                "abi",
                "evm.bytecode",
                "evm.deployedBytecode",
                "evm.methodIdentifiers",
                "metadata"
              ],
              "": [
                "ast"
              ]
            }
          }
        }
      },
      "imports": [],
      "versionPragmas": [
        ">=0.4.22 <0.9.0"
      ],
      "artifacts": [
        "console"
      ]
    }
  }
}
